[
  {
    "date": "2012-01-03T00:00:00.000Z",
    "close": 14.04,
    "high": 14.4,
    "low": 14.01,
    "open": 14.3,
    "volume": 11701100,
    "adjClose": 0.3218563358,
    "adjHigh": 0.3301090623,
    "adjLow": 0.3211686086,
    "adjOpen": 0.3278166383,
    "adjVolume": 468044000,
    "divCash": 0.0,
    "splitFactor": 1.0
  },
  {
    "date": "2012-01-04T00:00:00.000Z",
    "close": 14.2,
    "high": 14.26,
    "low": 13.92,
    "open": 14.04,
    "volume": 8684300,
    "adjClose": 0.3255242143,
    "adjHigh": 0.3268996687,
    "adjLow": 0.3191054269,
    "adjOpen": 0.3218563358,
    "adjVolume": 347372000,
    "divCash": 0.0,
    "splitFactor": 1.0
  },
  {
    "date": "2012-01-05T00:00:00.000Z",
    "close": 14.71,
    "high": 14.78,
    "low": 14.07,
    "open": 14.13,
    "volume": 14088700,
    "adjClose": 0.3372155769,
    "adjHigh": 0.3388202737,
    "adjLow": 0.322544063,
    "adjOpen": 0.3239195174,
    "adjVolume": 563548000,
    "divCash": 0.0,
    "splitFactor": 1.0
  },
  {
    "date": "2012-01-06T00:00:00.000Z",
    "close": 14.54,
    "high": 14.71,
    "low": 14.37,
    "open": 14.7,
    "volume": 13331300,
    "adjClose": 0.333318456,
    "adjHigh": 0.3372155769,
    "adjLow": 0.3294213351,
    "adjOpen": 0.3369863345,
    "adjVolume": 533252000,
    "divCash": 0.0,
    "splitFactor": 1.0
  },
  {
    "date": "2012-01-09T00:00:00.000Z",
    "close": 14.54,
    "high": 14.82,
    "low": 14.44,
    "open": 14.55,
    "volume": 12706100,
    "adjClose": 0.333318456,
    "adjHigh": 0.3397372433,
    "adjLow": 0.331026032,
    "adjOpen": 0.3335476984,
    "adjVolume": 508244000,
    "divCash": 0.0,
    "splitFactor": 1.0
  },
  {
    "date": "2012-01-10T00:00:00.000Z",
    "close": 14.48,
    "high": 14.77,
    "low": 14.38,
    "open": 14.76,
    "volume": 13658200,
    "adjClose": 0.3319430016,
    "adjHigh": 0.3385910313,
    "adjLow": 0.3296505775,
    "adjOpen": 0.3383617889,
    "adjVolume": 546328000,
    "divCash": 0.0,
    "splitFactor": 1.0
  },
  {
    "date": "2012-01-11T00:00:00.000Z",
    "close": 14.19,
    "high": 14.48,
    "low": 14.13,
    "open": 14.35,
    "volume": 12106800,
    "adjClose": 0.3252949719,
    "adjHigh": 0.3319430016,
    "adjLow": 0.3239195174,
    "adjOpen": 0.3289628503,
    "adjVolume": 484272000,
    "divCash": 0.0,
    "splitFactor": 1.0
  },
  {
    "date": "2012-01-12T00:00:00.000Z",
    "close": 14.1,
    "high": 14.23,
    "low": 13.79,
    "open": 14.22,
    "volume": 16309100,
    "adjClose": 0.3232317902,
    "adjHigh": 0.3262119415,
    "adjLow": 0.3161252757,
    "adjOpen": 0.3259826991,
    "adjVolume": 652364000,
    "divCash": 0.0,
    "splitFactor": 1.0
  },
  {
    "date": "2012-01-13T00:00:00.000Z",
    "close": 13.73,
    "high": 14.03,
    "low": 13.66,
    "open": 14.0,
    "volume": 12607500,
    "adjClose": 0.3147498212,
    "adjHigh": 0.3216270934,
    "adjLow": 0.3131451244,
    "adjOpen": 0.3209393662,
    "adjVolume": 504300000,
    "divCash": 0.0,
    "splitFactor": 1.0
  },
  {
    "date": "2012-01-17T00:00:00.000Z",
    "close": 13.52,
    "high": 13.94,
    "low": 13.5,
    "open": 13.94,
    "volume": 15679400,
    "adjClose": 0.3099357308,
    "adjHigh": 0.3195639117,
    "adjLow": 0.3094772459,
    "adjOpen": 0.3195639117,
    "adjVolume": 627176000,
    "divCash": 0.0,
    "splitFactor": 1.0
  },
  {
    "date": "2012-01-18T00:00:00.000Z",
    "close": 13.98,
    "high": 14.09,
    "low": 13.705,
    "open": 13.78,
    "volume": 15816900,
    "adjClose": 0.3204808814,
    "adjHigh": 0.3230025478,
    "adjLow": 0.3141767152,
    "adjOpen": 0.3158960333,
    "adjVolume": 632676000,
    "divCash": 0.0,
    "splitFactor": 1.0
  },
  {
    "date": "2012-01-19T00:00:00.000Z",
    "close": 14.35,
    "high": 14.37,
    "low": 13.9502,
    "open": 14.1,
    "volume": 15207800,
    "adjClose": 0.3289628503,
    "adjHigh": 0.3294213351,
    "adjLow": 0.319797739,
    "adjOpen": 0.3232317902,
    "adjVolume": 608312000,
    "divCash": 0.0,
    "splitFactor": 1.0
  },
  {
    "date": "2012-01-20T00:00:00.000Z",
    "close": 14.22,
    "high": 14.5,
    "low": 14.17,
    "open": 14.33,
    "volume": 13656800,
    "adjClose": 0.3259826991,
    "adjHigh": 0.3324014864,
    "adjLow": 0.324836487,
    "adjOpen": 0.3285043655,
    "adjVolume": 546272000,
    "divCash": 0.0,
    "splitFactor": 1.0
  },
  {
    "date": "2012-01-23T00:00:00.000Z",
    "close": 14.61,
    "high": 14.62,
    "low": 14.05,
    "open": 14.23,
    "volume": 14069800,
    "adjClose": 0.3349231528,
    "adjHigh": 0.3351523952,
    "adjLow": 0.3220855782,
    "adjOpen": 0.3262119415,
    "adjVolume": 562792000,
    "divCash": 0.0,
    "splitFactor": 1.0
  },
  {
    "date": "2012-01-24T00:00:00.000Z",
    "close": 14.94,
    "high": 15.0,
    "low": 14.5,
    "open": 14.51,
    "volume": 18273000,
    "adjClose": 0.3424881522,
    "adjHigh": 0.3438636066,
    "adjLow": 0.3324014864,
    "adjOpen": 0.3326307288,
    "adjVolume": 730920000,
    "divCash": 0.0,
    "splitFactor": 1.0
  },
  {
    "date": "2012-01-25T00:00:00.000Z",
    "close": 14.85,
    "high": 14.89,
    "low": 14.12,
    "open": 14.54,
    "volume": 31853800,
    "adjClose": 0.3404249705,
    "adjHigh": 0.3413419402,
    "adjLow": 0.323690275,
    "adjOpen": 0.333318456,
    "adjVolume": 1274152000,
    "divCash": 0.0,
    "splitFactor": 1.0
  },
  {
    "date": "2012-01-26T00:00:00.000Z",
    "close": 14.71,
    "high": 15.24,
    "low": 14.63,
    "open": 15.07,
    "volume": 19991800,
    "adjClose": 0.3372155769,
    "adjHigh": 0.3493654243,
    "adjLow": 0.3353816376,
    "adjOpen": 0.3454683034,
    "adjVolume": 799672000,
    "divCash": 0.0,
    "splitFactor": 1.0
  },
  {
    "date": "2012-01-27T00:00:00.000Z",
    "close": 14.91,
    "high": 14.99,
    "low": 14.5,
    "open": 14.62,
    "volume": 11249900,
    "adjClose": 0.341800425,
    "adjHigh": 0.3436343642,
    "adjLow": 0.3324014864,
    "adjOpen": 0.3351523952,
    "adjVolume": 449996000,
    "divCash": 0.0,
    "splitFactor": 1.0
  },
  {
    "date": "2012-01-30T00:00:00.000Z",
    "close": 14.8,
    "high": 14.87,
    "low": 14.43,
    "open": 14.65,
    "volume": 9976900,
    "adjClose": 0.3392787585,
    "adjHigh": 0.3408834554,
    "adjLow": 0.3307967896,
    "adjOpen": 0.3358401225,
    "adjVolume": 399076000,
    "divCash": 0.0,
    "splitFactor": 1.0
  },
  {
    "date": "2012-01-31T00:00:00.000Z",
    "close": 14.77,
    "high": 14.85,
    "low": 14.51,
    "open": 14.84,
    "volume": 8947500,
    "adjClose": 0.3385910313,
    "adjHigh": 0.3404249705,
    "adjLow": 0.3326307288,
    "adjOpen": 0.3401957281,
    "adjVolume": 357900000,
    "divCash": 0.0,
    "splitFactor": 1.0
  }
]